{
  "hash": "095a4b55",
  "configHash": "eb645978",
  "lockfileHash": "28d06974",
  "browserHash": "aad1ffcf",
  "optimized": {
    "react/jsx-dev-runtime": {
      "src": "../../node_modules/react/jsx-dev-runtime.js",
      "file": "react_jsx-dev-runtime.js",
      "fileHash": "fe2c7cd1",
      "needsInterop": true
    },
    "react": {
      "src": "../../node_modules/react/index.js",
      "file": "react.js",
      "fileHash": "0fdaf219",
      "needsInterop": true
    },
    "react-dom/client": {
      "src": "../../node_modules/react-dom/client.js",
      "file": "react-dom_client.js",
      "fileHash": "016c517d",
      "needsInterop": true
    },
    "lucide-react": {
      "src": "../../node_modules/lucide-react/dist/esm/lucide-react.js",
      "file": "lucide-react.js",
      "fileHash": "363863fd",
      "needsInterop": false
    },
    "@emailjs/browser": {
      "src": "../../node_modules/@emailjs/browser/es/index.js",
      "file": "@emailjs_browser.js",
      "fileHash": "671aae23",
      "needsInterop": false
    }
  },
  "chunks": {
    "chunk-4BPZ7PBZ": {
      "file": "chunk-4BPZ7PBZ.js"
    },
    "chunk-G3PMV62Z": {
      "file": "chunk-G3PMV62Z.js"
    }
  }
}